devpi_tokens/__init__.py
devpi_tokens/client.py
devpi_tokens/restrictions.py
devpi_tokens/server.py
devpi_tokens/views.py
devpi_tokens/tests/test_client.py
devpi_tokens/tests/test_functional.py
devpi_tokens/tests/test_server.py
devpi_tokens-1.1.0.dist-info/licenses/LICENSE
devpi_tokens-1.1.0.dist-info/METADATA
devpi_tokens-1.1.0.dist-info/WHEEL
devpi_tokens-1.1.0.dist-info/entry_points.txt
devpi_tokens-1.1.0.dist-info/top_level.txt
devpi_tokens-1.1.0.dist-info/zip-safe
devpi_tokens-1.1.0.dist-info/RECORD
