Metadata-Version: 2.4
Name: devpi-tokens
Version: 1.1.0
Summary: "devpi-tokens: add support for constrained access tokens to devpi-client and devpi-server"
Home-page: https://github.com/devpi/devpi-tokens
Author: Florian Schulze and Contributors
Author-email: mail@florian-schulze.net
License: MIT
Project-URL: Bug Tracker, https://github.com/devpi/devpi-tokens/issues
Project-URL: Source Code, https://github.com/devpi/devpi-tokens
Classifier: Development Status :: 5 - Production/Stable
Classifier: Environment :: Plugins
Classifier: Intended Audience :: Developers
Classifier: Intended Audience :: System Administrators
Classifier: License :: OSI Approved :: MIT License
Classifier: Operating System :: POSIX
Classifier: Operating System :: Microsoft :: Windows
Classifier: Operating System :: MacOS :: MacOS X
Classifier: Topic :: Utilities
Classifier: Programming Language :: Python :: 3
Classifier: Programming Language :: Python :: 3.8
Classifier: Programming Language :: Python :: 3.9
Classifier: Programming Language :: Python :: 3.10
Classifier: Programming Language :: Python :: 3.11
Classifier: Programming Language :: Python :: 3.12
Classifier: Programming Language :: Python :: 3.13
Requires-Python: >=3.8
License-File: LICENSE
Requires-Dist: pymacaroons
Provides-Extra: client
Requires-Dist: delta; extra == "client"
Requires-Dist: devpi-client>=4.3.0; extra == "client"
Provides-Extra: server
Requires-Dist: devpi-server>=6.10.0; extra == "server"
Dynamic: license-file
